browser_cookie3/__init__.py
browser_cookie3-0.19.1.dist-info/LICENSE
browser_cookie3-0.19.1.dist-info/METADATA
browser_cookie3-0.19.1.dist-info/WHEEL
browser_cookie3-0.19.1.dist-info/top_level.txt
browser_cookie3-0.19.1.dist-info/RECORD
